pytwobodyorbit.py
pytwobodyorbit-1.0.0.dist-info/LICENSE.txt
pytwobodyorbit-1.0.0.dist-info/METADATA
pytwobodyorbit-1.0.0.dist-info/WHEEL
pytwobodyorbit-1.0.0.dist-info/top_level.txt
pytwobodyorbit-1.0.0.dist-info/RECORD
