Metadata-Version: 2.1
Name: pytwobodyorbit
Version: 1.0.0
Summary: A module that provides various computations about two-body orbits
Home-page: https://github.com/whiskie14142/pytwobodyorbit
Author: whiskie14142
Author-email: whiskie14142@gmail.com
License: MIT
Keywords: two-body orbit Keplerian Cartesian Lambert
Platform: UNKNOWN
Classifier: Development Status :: 5 - Production/Stable
Classifier: Programming Language :: Python :: 3
Classifier: License :: OSI Approved :: MIT License
Classifier: Operating System :: OS Independent
